proxyscrapertool/__init__.py
proxyscrapertool/example.py
proxyscrapertool-0.0.2.dist-info/METADATA
proxyscrapertool-0.0.2.dist-info/WHEEL
proxyscrapertool-0.0.2.dist-info/top_level.txt
proxyscrapertool-0.0.2.dist-info/RECORD
