Metadata-Version: 2.1
Name: proxyscrapertool
Version: 0.0.2
Summary: Free proxy scraper tool!
Author-email: John Pork <johnpork@hello.com>
Project-URL: Homepage, https://github.com/pypa/sampleproject
Project-URL: Bug Tracker, https://github.com/pypa/sampleproject/issues
Classifier: Programming Language :: Python :: 3
Classifier: License :: OSI Approved :: MIT License
Classifier: Operating System :: OS Independent
Requires-Python: >=3.7
